aircv/__init__.py
aircv-1.4.6.dist-info/DESCRIPTION.rst
aircv-1.4.6.dist-info/METADATA
aircv-1.4.6.dist-info/RECORD
aircv-1.4.6.dist-info/WHEEL
aircv-1.4.6.dist-info/metadata.json
aircv-1.4.6.dist-info/pbr.json
aircv-1.4.6.dist-info/top_level.txt
