Metadata-Version: 2.0
Name: aircv
Version: 1.4.6
Summary: Find object position based on python-opencv2.
Home-page: https://github.com/netease/aircv
Author: codeskyblue
Author-email: codeskyblue@gmail.com
License: MIT
Platform: UNKNOWN
Classifier: Environment :: Console
Classifier: Intended Audience :: Developers
Classifier: Operating System :: OS Independent
Classifier: Programming Language :: Python
